manatus/__init__.py
manatus/__main__.py
manatus/exceptions.py
manatus/maps.py
manatus/organizations.py
manatus/scenarios.py
manatus/source_resource.py
manatus/cli/__init__.py
manatus/cli/harvest.py
manatus/cli/transform.py
manatus/tests/__init__.py
manatus/tests/exceptions_test.py
manatus/tests/harvest_test.py
manatus/tests/maps_test.py
manatus/tests/organiztions_test.py
manatus/tests/scenarios_test.py
manatus/tests/source_resource_test.py
manatus/tests/transform_test.py
manatus/tests/test_data/DCdebugSmall.xml
manatus/tests/test_data/FlMemSmall.xml
manatus/tests/test_data/MODSdebugSmall.xml
manatus/tests/test_data/QDCdebugSmall.xml
manatus/tests/test_data/fsu_susanbradfordeppespapers.xml
manatus/tests/test_data/record_group_error_test
manatus/tests/test_data/record_group_json.json
manatus/tests/test_data/record_group_jsonl.jsonl
manatus/tests/test_data/test_scenario_config.cfg
manatus/tests/test_data/um_chc0336.xml
manatus/tests/test_data/usf_boucicault.xml
manatus/tests/test_data/dc/usf_boucicault.xml
manatus/tests/test_data/mods/fsu_susanbradfordeppespapers.xml
manatus/tests/test_data/qdc/um_chc0336.xml
manatus-1.0.15.dist-info/AUTHORS.rst
manatus-1.0.15.dist-info/LICENSE
manatus-1.0.15.dist-info/METADATA
manatus-1.0.15.dist-info/WHEEL
manatus-1.0.15.dist-info/top_level.txt
manatus-1.0.15.dist-info/RECORD
