Metadata-Version: 2.1
Name: manatus
Version: 1.0.15
Summary: Metadata aggregation and transformation library
Home-page: http://github.com/SunshineStateDigitalNetwork/manatus
Author: Matthew Miguez
Author-email: r.m.miguez@gmail.com
License: MIT
Keywords: oai-pmh metadata digital-libraries
Platform: any
Classifier: Development Status :: 4 - Beta
Classifier: License :: OSI Approved :: GNU General Public License v3 (GPLv3)
Classifier: Programming Language :: Python :: 3.8
Classifier: Programming Language :: Python :: 3.9
Classifier: Programming Language :: Python :: 3.10
Classifier: Programming Language :: Python :: 3.11
Classifier: Topic :: Text Processing :: Markup :: XML
License-File: LICENSE
License-File: AUTHORS.rst
Requires-Dist: pymods >=2.0.9
Requires-Dist: sickle >=0.7.0
Requires-Dist: requests
